dvc_yadisk/__init__.py
dvc_yadisk/afs.py
dvc_yadisk/cli.py
dvc_yadisk/fs.py
dvc_yadisk/py.typed
dvc_yadisk-0.1.8.dist-info/METADATA
dvc_yadisk-0.1.8.dist-info/WHEEL
dvc_yadisk-0.1.8.dist-info/entry_points.txt
dvc_yadisk-0.1.8.dist-info/licenses/LICENSE
dvc_yadisk-0.1.8.dist-info/RECORD
