Metadata-Version: 2.4
Name: dvc-yadisk
Version: 0.1.8
Summary: Yandex Disk remote storage plugin for DVC
Project-URL: Homepage, https://github.com/suro4ek/dvc-yadisk
Project-URL: Repository, https://github.com/suro4ek/dvc-yadisk
Project-URL: Issues, https://github.com/suro4ek/dvc-yadisk/issues
Author-email: suro4ek <timu.zaxarov@gmail.com>
License-Expression: Apache-2.0
License-File: LICENSE
Keywords: data-version-control,dvc,mlops,storage,yadisk,yandex,yandex-disk
Classifier: Development Status :: 4 - Beta
Classifier: License :: OSI Approved :: Apache Software License
Classifier: Operating System :: OS Independent
Classifier: Programming Language :: Python :: 3
Classifier: Programming Language :: Python :: 3.9
Classifier: Programming Language :: Python :: 3.10
Classifier: Programming Language :: Python :: 3.11
Classifier: Programming Language :: Python :: 3.12
Classifier: Programming Language :: Python :: 3.13
Requires-Python: >=3.9
Requires-Dist: dvc>=3.0.0
Requires-Dist: httpx>=0.24.0
Requires-Dist: yadisk>=3.0.0
Provides-Extra: dev
Requires-Dist: mypy>=1.0; extra == 'dev'
Requires-Dist: pytest-asyncio>=0.21; extra == 'dev'
Requires-Dist: pytest-mock>=3.10; extra == 'dev'
Requires-Dist: pytest>=7.0; extra == 'dev'
Requires-Dist: ruff>=0.1.0; extra == 'dev'
